mopinion/__init__.py
mopinion/client.py
mopinion/dataclasses.py
mopinion/settings.py
mopinion-1.0.1.dist-info/LICENSE
mopinion-1.0.1.dist-info/METADATA
mopinion-1.0.1.dist-info/WHEEL
mopinion-1.0.1.dist-info/top_level.txt
mopinion-1.0.1.dist-info/RECORD
