Metadata-Version: 2.1
Name: mopinion
Version: 1.0.1
Summary: A client library for the Mopinion Data API
Home-page: https://github.com/Mopinion-com/mopinion-python-api
Author: Mopinion
Author-email: 
License: MIT License
Keywords: mopinion
Classifier: Programming Language :: Python :: 3
Classifier: License :: OSI Approved :: MIT License
Classifier: Operating System :: OS Independent
Requires-Python: >=3.6
License-File: LICENSE
Requires-Dist: requests
Requires-Dist: dataclasses ; python_version < "3.7.0"
Provides-Extra: test
Requires-Dist: requests ; extra == 'test'
Requires-Dist: pytest ; extra == 'test'
Requires-Dist: mock ; extra == 'test'
Requires-Dist: dataclasses ; (python_version < "3.7.0") and extra == 'test'
